{
  "session_id": "6e103032-078a-4198-ba3c-3e77f6907718",
  "project_path": "/Users/rocky243/paimon.finance/paimon-rwa-contracts",
  "start_time": "2026-03-09T01:39:31.811Z",
  "duration_minutes": 195,
  "user_message_count": 19,
  "assistant_message_count": 129,
  "tool_counts": {
    "Skill": 1,
    "Read": 10,
    "ToolSearch": 2,
    "TaskCreate": 12,
    "TaskUpdate": 17,
    "Bash": 9,
    "Write": 6,
    "Edit": 6,
    "WebSearch": 8,
    "WebFetch": 2
  },
  "languages": {
    "Markdown": 20
  },
  "git_commits": 0,
  "git_pushes": 0,
  "input_tokens": 3943,
  "output_tokens": 43068,
  "first_prompt": "还记得我们聊过什么吗 刚刚",
  "user_interruptions": 0,
  "user_response_times": [
    66.157,
    159.347,
    159.347,
    50.384,
    51.032,
    1002.567,
    518.252,
    1075.398,
    1075.398,
    16.58,
    228.994,
    143.281,
    326.725,
    632.072
  ],
  "tool_errors": 2,
  "tool_error_categories": {
    "Other": 2
  },
  "uses_task_agent": false,
  "uses_mcp": false,
  "uses_web_search": true,
  "uses_web_fetch": true,
  "lines_added": 1052,
  "lines_removed": 24,
  "files_modified": 6,
  "message_hours": [
    9,
    9,
    9,
    9,
    9,
    9,
    9,
    10,
    10,
    10,
    10,
    10,
    10,
    10,
    10,
    10,
    11,
    12,
    12
  ],
  "user_message_timestamps": [
    "2026-03-09T01:39:46.524Z",
    "2026-03-09T01:41:06.322Z",
    "2026-03-09T01:44:27.806Z",
    "2026-03-09T01:44:27.806Z",
    "2026-03-09T01:47:26.687Z",
    "2026-03-09T01:48:26.276Z",
    "2026-03-09T01:48:29.236Z",
    "2026-03-09T02:06:50.530Z",
    "2026-03-09T02:16:01.167Z",
    "2026-03-09T02:34:44.925Z",
    "2026-03-09T02:34:44.925Z",
    "2026-03-09T02:36:54.091Z",
    "2026-03-09T02:40:45.932Z",
    "2026-03-09T02:40:50.296Z",
    "2026-03-09T02:44:57.995Z",
    "2026-03-09T02:53:10.318Z",
    "2026-03-09T03:04:06.232Z",
    "2026-03-09T04:52:41.114Z",
    "2026-03-09T04:52:41.114Z"
  ]
}